[
    {
        "id": 1,
        "nombre": "Cristián",
        "apellido": "Rodríguez",
        "correo": "cris.rodrigueza@duocuc.cl",
        "tipo": "alumno",
        "contrasena": "1234"
    },
    {
        "id": 2,
        "nombre": "Sebastian",
        "apellido": "Rimmelin",
        "correo": "se.rimmelin@duocuc.cl",
        "tipo": "alumno",
        "contrasena": "1234"
    },
    {
        "id": 3,
        "nombre": "Ronald",
        "apellido": "Ulloa",
        "correo": "ron.ulloa@duocuc.cl",
        "tipo": "alumno",
        "contrasena": "1234"
    },
    {
        "id": 4,
        "nombre": "Julio",
        "apellido": "Herrera",
        "correo": "ju.herrerau@profesor.duoc.cl",
        "tipo": "profesor",
        "contrasena": "1234"
    }
]
